cfpm/__init__.py
cfpm/console.py
cfpm/log.py
cfpm-0.0.0.dist-info/entry_points.txt
cfpm-0.0.0.dist-info/LICENSE
cfpm-0.0.0.dist-info/WHEEL
cfpm-0.0.0.dist-info/METADATA
cfpm-0.0.0.dist-info/RECORD
